<annotation>
	<folder>caise</folder>
	<filename>159.jpg</filename>
	<path>D:\zaopian\caise\159.jpg</path>
	<source>
		<database>Unknown</database>
	</source>
	<size>
		<width>4032</width>
		<height>3024</height>
		<depth>3</depth>
	</size>
	<segmented>0</segmented>
	<object>
		<name>termite</name>
		<pose>Unspecified</pose>
		<truncated>0</truncated>
		<difficult>0</difficult>
		<bndbox>
			<xmin>2607</xmin>
			<ymin>1456</ymin>
			<xmax>2716</xmax>
			<ymax>1576</ymax>
		</bndbox>
	</object>
	<object>
		<name>termite</name>
		<pose>Unspecified</pose>
		<truncated>0</truncated>
		<difficult>0</difficult>
		<bndbox>
			<xmin>2099</xmin>
			<ymin>1196</ymin>
			<xmax>2220</xmax>
			<ymax>1255</ymax>
		</bndbox>
	</object>
	<object>
		<name>termite</name>
		<pose>Unspecified</pose>
		<truncated>0</truncated>
		<difficult>0</difficult>
		<bndbox>
			<xmin>2664</xmin>
			<ymin>1631</ymin>
			<xmax>2720</xmax>
			<ymax>1769</ymax>
		</bndbox>
	</object>
	<object>
		<name>termite</name>
		<pose>Unspecified</pose>
		<truncated>0</truncated>
		<difficult>0</difficult>
		<bndbox>
			<xmin>2587</xmin>
			<ymin>1686</ymin>
			<xmax>2647</xmax>
			<ymax>1802</ymax>
		</bndbox>
	</object>
	<object>
		<name>termite</name>
		<pose>Unspecified</pose>
		<truncated>0</truncated>
		<difficult>0</difficult>
		<bndbox>
			<xmin>2589</xmin>
			<ymin>1582</ymin>
			<xmax>2636</xmax>
			<ymax>1660</ymax>
		</bndbox>
	</object>
	<object>
		<name>termite</name>
		<pose>Unspecified</pose>
		<truncated>0</truncated>
		<difficult>0</difficult>
		<bndbox>
			<xmin>2633</xmin>
			<ymin>1555</ymin>
			<xmax>2679</xmax>
			<ymax>1680</ymax>
		</bndbox>
	</object>
	<object>
		<name>termite</name>
		<pose>Unspecified</pose>
		<truncated>0</truncated>
		<difficult>0</difficult>
		<bndbox>
			<xmin>3100</xmin>
			<ymin>1600</ymin>
			<xmax>3217</xmax>
			<ymax>1749</ymax>
		</bndbox>
	</object>
	<object>
		<name>termite</name>
		<pose>Unspecified</pose>
		<truncated>0</truncated>
		<difficult>0</difficult>
		<bndbox>
			<xmin>1853</xmin>
			<ymin>699</ymin>
			<xmax>1984</xmax>
			<ymax>795</ymax>
		</bndbox>
	</object>
</annotation>
