<annotation>
	<folder>caise</folder>
	<filename>200.jpg</filename>
	<path>D:\zaopian\caise\200.jpg</path>
	<source>
		<database>Unknown</database>
	</source>
	<size>
		<width>4032</width>
		<height>3024</height>
		<depth>3</depth>
	</size>
	<segmented>0</segmented>
	<object>
		<name>termite</name>
		<pose>Unspecified</pose>
		<truncated>0</truncated>
		<difficult>0</difficult>
		<bndbox>
			<xmin>3552</xmin>
			<ymin>1601</ymin>
			<xmax>3690</xmax>
			<ymax>1653</ymax>
		</bndbox>
	</object>
	<object>
		<name>termite</name>
		<pose>Unspecified</pose>
		<truncated>0</truncated>
		<difficult>0</difficult>
		<bndbox>
			<xmin>3433</xmin>
			<ymin>1584</ymin>
			<xmax>3545</xmax>
			<ymax>1648</ymax>
		</bndbox>
	</object>
	<object>
		<name>termite</name>
		<pose>Unspecified</pose>
		<truncated>0</truncated>
		<difficult>0</difficult>
		<bndbox>
			<xmin>3048</xmin>
			<ymin>1688</ymin>
			<xmax>3154</xmax>
			<ymax>1773</ymax>
		</bndbox>
	</object>
	<object>
		<name>termite</name>
		<pose>Unspecified</pose>
		<truncated>0</truncated>
		<difficult>0</difficult>
		<bndbox>
			<xmin>3182</xmin>
			<ymin>1414</ymin>
			<xmax>3284</xmax>
			<ymax>1466</ymax>
		</bndbox>
	</object>
	<object>
		<name>termite</name>
		<pose>Unspecified</pose>
		<truncated>0</truncated>
		<difficult>0</difficult>
		<bndbox>
			<xmin>3277</xmin>
			<ymin>1454</ymin>
			<xmax>3378</xmax>
			<ymax>1531</ymax>
		</bndbox>
	</object>
	<object>
		<name>termite</name>
		<pose>Unspecified</pose>
		<truncated>0</truncated>
		<difficult>0</difficult>
		<bndbox>
			<xmin>3440</xmin>
			<ymin>1775</ymin>
			<xmax>3552</xmax>
			<ymax>1865</ymax>
		</bndbox>
	</object>
	<object>
		<name>termite</name>
		<pose>Unspecified</pose>
		<truncated>0</truncated>
		<difficult>0</difficult>
		<bndbox>
			<xmin>2248</xmin>
			<ymin>1204</ymin>
			<xmax>2307</xmax>
			<ymax>1339</ymax>
		</bndbox>
	</object>
	<object>
		<name>termite</name>
		<pose>Unspecified</pose>
		<truncated>0</truncated>
		<difficult>0</difficult>
		<bndbox>
			<xmin>2138</xmin>
			<ymin>1229</ymin>
			<xmax>2209</xmax>
			<ymax>1348</ymax>
		</bndbox>
	</object>
	<object>
		<name>termite</name>
		<pose>Unspecified</pose>
		<truncated>0</truncated>
		<difficult>0</difficult>
		<bndbox>
			<xmin>2308</xmin>
			<ymin>1350</ymin>
			<xmax>2427</xmax>
			<ymax>1405</ymax>
		</bndbox>
	</object>
	<object>
		<name>termite</name>
		<pose>Unspecified</pose>
		<truncated>0</truncated>
		<difficult>0</difficult>
		<bndbox>
			<xmin>2273</xmin>
			<ymin>1391</ymin>
			<xmax>2360</xmax>
			<ymax>1453</ymax>
		</bndbox>
	</object>
	<object>
		<name>termite</name>
		<pose>Unspecified</pose>
		<truncated>0</truncated>
		<difficult>0</difficult>
		<bndbox>
			<xmin>2349</xmin>
			<ymin>1401</ymin>
			<xmax>2463</xmax>
			<ymax>1455</ymax>
		</bndbox>
	</object>
	<object>
		<name>termite</name>
		<pose>Unspecified</pose>
		<truncated>0</truncated>
		<difficult>0</difficult>
		<bndbox>
			<xmin>2207</xmin>
			<ymin>1371</ymin>
			<xmax>2285</xmax>
			<ymax>1468</ymax>
		</bndbox>
	</object>
	<object>
		<name>termite</name>
		<pose>Unspecified</pose>
		<truncated>0</truncated>
		<difficult>0</difficult>
		<bndbox>
			<xmin>1982</xmin>
			<ymin>1420</ymin>
			<xmax>2068</xmax>
			<ymax>1525</ymax>
		</bndbox>
	</object>
	<object>
		<name>termite</name>
		<pose>Unspecified</pose>
		<truncated>0</truncated>
		<difficult>0</difficult>
		<bndbox>
			<xmin>1987</xmin>
			<ymin>1336</ymin>
			<xmax>2053</xmax>
			<ymax>1418</ymax>
		</bndbox>
	</object>
	<object>
		<name>termite</name>
		<pose>Unspecified</pose>
		<truncated>0</truncated>
		<difficult>0</difficult>
		<bndbox>
			<xmin>1827</xmin>
			<ymin>1265</ymin>
			<xmax>1924</xmax>
			<ymax>1336</ymax>
		</bndbox>
	</object>
	<object>
		<name>termite</name>
		<pose>Unspecified</pose>
		<truncated>0</truncated>
		<difficult>0</difficult>
		<bndbox>
			<xmin>1653</xmin>
			<ymin>1253</ymin>
			<xmax>1792</xmax>
			<ymax>1325</ymax>
		</bndbox>
	</object>
	<object>
		<name>termite</name>
		<pose>Unspecified</pose>
		<truncated>0</truncated>
		<difficult>0</difficult>
		<bndbox>
			<xmin>1729</xmin>
			<ymin>1473</ymin>
			<xmax>1864</xmax>
			<ymax>1534</ymax>
		</bndbox>
	</object>
	<object>
		<name>termite</name>
		<pose>Unspecified</pose>
		<truncated>0</truncated>
		<difficult>0</difficult>
		<bndbox>
			<xmin>1610</xmin>
			<ymin>1519</ymin>
			<xmax>1705</xmax>
			<ymax>1596</ymax>
		</bndbox>
	</object>
	<object>
		<name>termite</name>
		<pose>Unspecified</pose>
		<truncated>0</truncated>
		<difficult>0</difficult>
		<bndbox>
			<xmin>1735</xmin>
			<ymin>1583</ymin>
			<xmax>1830</xmax>
			<ymax>1661</ymax>
		</bndbox>
	</object>
</annotation>
